{
  "kind": "Endpoints",
  "apiVersion": "v1",
  "metadata": {
    "name": "glusterfs-cluster"
  },
  "subsets": [
    {
      "addresses": [
        {
          "ip": "52.91.208.229"
        }
      ],
      "ports": [
        {
          "port": 1
        }
      ]
    },
    {
      "addresses": [
        {
          "ip": "54.82.187.175"
        }
      ],
      "ports": [
        {
          "port": 1
        }
      ]
    },
    {
      "addresses": [
        {
          "ip": "54.159.34.74"
        }
      ],
      "ports": [
        {
          "port": 1
        }
      ]
    }

  ]
}
